{
  "description": "GlobalInClusterIPPool is the Schema for the global inclusterippools API.\nThis pool type is cluster scoped. IPAddressClaims can reference\npools of this type from any namespace.",
  "properties": {
    "apiVersion": {
      "description": "APIVersion defines the versioned schema of this representation of an object.\nServers should convert recognized schemas to the latest internal value, and\nmay reject unrecognized values.\nMore info: https://git.k8s.io/community/contributors/devel/sig-architecture/api-conventions.md#resources",
      "type": "string"
    },
    "kind": {
      "description": "Kind is a string value representing the REST resource this object represents.\nServers may infer this from the endpoint the client submits requests to.\nCannot be updated.\nIn CamelCase.\nMore info: https://git.k8s.io/community/contributors/devel/sig-architecture/api-conventions.md#types-kinds",
      "type": "string"
    },
    "metadata": {
      "type": "object"
    },
    "spec": {
      "description": "InClusterIPPoolSpec defines the desired state of InClusterIPPool.",
      "properties": {
        "addresses": {
          "description": "Addresses is a list of IP addresses that can be assigned. This set of\naddresses can be non-contiguous. Can be omitted if subnet, or first and\nlast is set.",
          "items": {
            "type": "string"
          },
          "type": "array"
        },
        "end": {
          "description": "Last is the last address that can be assigned.\nMust come after first and needs to fit into a common subnet.\nIf unset, the second last address of subnet will be used.",
          "type": "string"
        },
        "gateway": {
          "description": "Gateway",
          "type": "string"
        },
        "prefix": {
          "description": "Prefix is the network prefix to use.\nIf unset the prefix from the subnet will be used.",
          "maximum": 128,
          "type": "integer"
        },
        "start": {
          "description": "First is the first address that can be assigned.\nIf unset, the second address of subnet will be used.",
          "type": "string"
        },
        "subnet": {
          "description": "Subnet is the subnet to assign IP addresses from.\nCan be omitted if addresses or first, last and prefix are set.",
          "type": "string"
        }
      },
      "type": "object",
      "additionalProperties": false
    },
    "status": {
      "description": "InClusterIPPoolStatus defines the observed state of InClusterIPPool.",
      "properties": {
        "ipAddresses": {
          "description": "Addresses reports the count of total, free, and used IPs in the pool.",
          "properties": {
            "free": {
              "description": "Free is the count of unallocated IPs in the pool.\nCounts greater than int can contain will report as math.MaxInt.",
              "type": "integer"
            },
            "outOfRange": {
              "description": "Out of Range is the count of allocated IPs in the pool that is not\ncontained within spec.Addresses.\nCounts greater than int can contain will report as math.MaxInt.",
              "type": "integer"
            },
            "total": {
              "description": "Total is the total number of IPs configured for the pool.\nCounts greater than int can contain will report as math.MaxInt.",
              "type": "integer"
            },
            "used": {
              "description": "Used is the count of allocated IPs in the pool.\nCounts greater than int can contain will report as math.MaxInt.",
              "type": "integer"
            }
          },
          "required": [
            "free",
            "outOfRange",
            "total",
            "used"
          ],
          "type": "object",
          "additionalProperties": false
        }
      },
      "type": "object",
      "additionalProperties": false
    }
  },
  "type": "object"
}
