{
  "description": "NetworkInsightsAnalysis is the Schema for the NetworkInsightsAnalysiss API. Provides a Network Insights Analysis resource.",
  "properties": {
    "apiVersion": {
      "description": "APIVersion defines the versioned schema of this representation of an object.\nServers should convert recognized schemas to the latest internal value, and\nmay reject unrecognized values.\nMore info: https://git.k8s.io/community/contributors/devel/sig-architecture/api-conventions.md#resources",
      "type": "string"
    },
    "kind": {
      "description": "Kind is a string value representing the REST resource this object represents.\nServers may infer this from the endpoint the client submits requests to.\nCannot be updated.\nIn CamelCase.\nMore info: https://git.k8s.io/community/contributors/devel/sig-architecture/api-conventions.md#types-kinds",
      "type": "string"
    },
    "metadata": {
      "type": "object"
    },
    "spec": {
      "description": "NetworkInsightsAnalysisSpec defines the desired state of NetworkInsightsAnalysis",
      "properties": {
        "deletionPolicy": {
          "default": "Delete",
          "description": "DeletionPolicy specifies what will happen to the underlying external\nwhen this managed resource is deleted - either \"Delete\" or \"Orphan\" the\nexternal resource.\nThis field is planned to be deprecated in favor of the ManagementPolicies\nfield in a future release. Currently, both could be set independently and\nnon-default values would be honored if the feature flag is enabled.\nSee the design doc for more information: https://github.com/crossplane/crossplane/blob/499895a25d1a1a0ba1604944ef98ac7a1a71f197/design/design-doc-observe-only-resources.md?plain=1#L223",
          "enum": [
            "Orphan",
            "Delete"
          ],
          "type": "string"
        },
        "forProvider": {
          "properties": {
            "filterInArns": {
              "description": "A list of ARNs for resources the path must traverse.",
              "items": {
                "type": "string"
              },
              "type": "array",
              "x-kubernetes-list-type": "set"
            },
            "networkInsightsPathId": {
              "description": "ID of the Network Insights Path to run an analysis on.",
              "type": "string"
            },
            "networkInsightsPathIdRef": {
              "description": "Reference to a NetworkInsightsPath in ec2 to populate networkInsightsPathId.",
              "properties": {
                "name": {
                  "description": "Name of the referenced object.",
                  "type": "string"
                },
                "policy": {
                  "description": "Policies for referencing.",
                  "properties": {
                    "resolution": {
                      "default": "Required",
                      "description": "Resolution specifies whether resolution of this reference is required.\nThe default is 'Required', which means the reconcile will fail if the\nreference cannot be resolved. 'Optional' means this reference will be\na no-op if it cannot be resolved.",
                      "enum": [
                        "Required",
                        "Optional"
                      ],
                      "type": "string"
                    },
                    "resolve": {
                      "description": "Resolve specifies when this reference should be resolved. The default\nis 'IfNotPresent', which will attempt to resolve the reference only when\nthe corresponding field is not present. Use 'Always' to resolve the\nreference on every reconcile.",
                      "enum": [
                        "Always",
                        "IfNotPresent"
                      ],
                      "type": "string"
                    }
                  },
                  "type": "object",
                  "additionalProperties": false
                }
              },
              "required": [
                "name"
              ],
              "type": "object",
              "additionalProperties": false
            },
            "networkInsightsPathIdSelector": {
              "description": "Selector for a NetworkInsightsPath in ec2 to populate networkInsightsPathId.",
              "properties": {
                "matchControllerRef": {
                  "description": "MatchControllerRef ensures an object with the same controller reference\nas the selecting object is selected.",
                  "type": "boolean"
                },
                "matchLabels": {
                  "additionalProperties": {
                    "type": "string"
                  },
                  "description": "MatchLabels ensures an object with matching labels is selected.",
                  "type": "object"
                },
                "policy": {
                  "description": "Policies for selection.",
                  "properties": {
                    "resolution": {
                      "default": "Required",
                      "description": "Resolution specifies whether resolution of this reference is required.\nThe default is 'Required', which means the reconcile will fail if the\nreference cannot be resolved. 'Optional' means this reference will be\na no-op if it cannot be resolved.",
                      "enum": [
                        "Required",
                        "Optional"
                      ],
                      "type": "string"
                    },
                    "resolve": {
                      "description": "Resolve specifies when this reference should be resolved. The default\nis 'IfNotPresent', which will attempt to resolve the reference only when\nthe corresponding field is not present. Use 'Always' to resolve the\nreference on every reconcile.",
                      "enum": [
                        "Always",
                        "IfNotPresent"
                      ],
                      "type": "string"
                    }
                  },
                  "type": "object",
                  "additionalProperties": false
                }
              },
              "type": "object",
              "additionalProperties": false
            },
            "region": {
              "description": "Region is the region you'd like your resource to be created in.",
              "type": "string"
            },
            "tags": {
              "additionalProperties": {
                "type": "string"
              },
              "description": "Key-value map of resource tags.",
              "type": "object",
              "x-kubernetes-map-type": "granular"
            },
            "waitForCompletion": {
              "description": "If enabled, the resource will wait for the Network Insights Analysis status to change to succeeded or failed. Setting this to false will skip the process. Default: true.",
              "type": "boolean"
            }
          },
          "required": [
            "region"
          ],
          "type": "object",
          "additionalProperties": false
        },
        "initProvider": {
          "description": "THIS IS A BETA FIELD. It will be honored\nunless the Management Policies feature flag is disabled.\nInitProvider holds the same fields as ForProvider, with the exception\nof Identifier and other resource reference fields. The fields that are\nin InitProvider are merged into ForProvider when the resource is created.\nThe same fields are also added to the terraform ignore_changes hook, to\navoid updating them after creation. This is useful for fields that are\nrequired on creation, but we do not desire to update them after creation,\nfor example because of an external controller is managing them, like an\nautoscaler.",
          "properties": {
            "filterInArns": {
              "description": "A list of ARNs for resources the path must traverse.",
              "items": {
                "type": "string"
              },
              "type": "array",
              "x-kubernetes-list-type": "set"
            },
            "networkInsightsPathId": {
              "description": "ID of the Network Insights Path to run an analysis on.",
              "type": "string"
            },
            "networkInsightsPathIdRef": {
              "description": "Reference to a NetworkInsightsPath in ec2 to populate networkInsightsPathId.",
              "properties": {
                "name": {
                  "description": "Name of the referenced object.",
                  "type": "string"
                },
                "policy": {
                  "description": "Policies for referencing.",
                  "properties": {
                    "resolution": {
                      "default": "Required",
                      "description": "Resolution specifies whether resolution of this reference is required.\nThe default is 'Required', which means the reconcile will fail if the\nreference cannot be resolved. 'Optional' means this reference will be\na no-op if it cannot be resolved.",
                      "enum": [
                        "Required",
                        "Optional"
                      ],
                      "type": "string"
                    },
                    "resolve": {
                      "description": "Resolve specifies when this reference should be resolved. The default\nis 'IfNotPresent', which will attempt to resolve the reference only when\nthe corresponding field is not present. Use 'Always' to resolve the\nreference on every reconcile.",
                      "enum": [
                        "Always",
                        "IfNotPresent"
                      ],
                      "type": "string"
                    }
                  },
                  "type": "object",
                  "additionalProperties": false
                }
              },
              "required": [
                "name"
              ],
              "type": "object",
              "additionalProperties": false
            },
            "networkInsightsPathIdSelector": {
              "description": "Selector for a NetworkInsightsPath in ec2 to populate networkInsightsPathId.",
              "properties": {
                "matchControllerRef": {
                  "description": "MatchControllerRef ensures an object with the same controller reference\nas the selecting object is selected.",
                  "type": "boolean"
                },
                "matchLabels": {
                  "additionalProperties": {
                    "type": "string"
                  },
                  "description": "MatchLabels ensures an object with matching labels is selected.",
                  "type": "object"
                },
                "policy": {
                  "description": "Policies for selection.",
                  "properties": {
                    "resolution": {
                      "default": "Required",
                      "description": "Resolution specifies whether resolution of this reference is required.\nThe default is 'Required', which means the reconcile will fail if the\nreference cannot be resolved. 'Optional' means this reference will be\na no-op if it cannot be resolved.",
                      "enum": [
                        "Required",
                        "Optional"
                      ],
                      "type": "string"
                    },
                    "resolve": {
                      "description": "Resolve specifies when this reference should be resolved. The default\nis 'IfNotPresent', which will attempt to resolve the reference only when\nthe corresponding field is not present. Use 'Always' to resolve the\nreference on every reconcile.",
                      "enum": [
                        "Always",
                        "IfNotPresent"
                      ],
                      "type": "string"
                    }
                  },
                  "type": "object",
                  "additionalProperties": false
                }
              },
              "type": "object",
              "additionalProperties": false
            },
            "tags": {
              "additionalProperties": {
                "type": "string"
              },
              "description": "Key-value map of resource tags.",
              "type": "object",
              "x-kubernetes-map-type": "granular"
            },
            "waitForCompletion": {
              "description": "If enabled, the resource will wait for the Network Insights Analysis status to change to succeeded or failed. Setting this to false will skip the process. Default: true.",
              "type": "boolean"
            }
          },
          "type": "object",
          "additionalProperties": false
        },
        "managementPolicies": {
          "default": [
            "*"
          ],
          "description": "THIS IS A BETA FIELD. It is on by default but can be opted out\nthrough a Crossplane feature flag.\nManagementPolicies specify the array of actions Crossplane is allowed to\ntake on the managed and external resources.\nThis field is planned to replace the DeletionPolicy field in a future\nrelease. Currently, both could be set independently and non-default\nvalues would be honored if the feature flag is enabled. If both are\ncustom, the DeletionPolicy field will be ignored.\nSee the design doc for more information: https://github.com/crossplane/crossplane/blob/499895a25d1a1a0ba1604944ef98ac7a1a71f197/design/design-doc-observe-only-resources.md?plain=1#L223\nand this one: https://github.com/crossplane/crossplane/blob/444267e84783136daa93568b364a5f01228cacbe/design/one-pager-ignore-changes.md",
          "items": {
            "description": "A ManagementAction represents an action that the Crossplane controllers\ncan take on an external resource.",
            "enum": [
              "Observe",
              "Create",
              "Update",
              "Delete",
              "LateInitialize",
              "*"
            ],
            "type": "string"
          },
          "type": "array"
        },
        "providerConfigRef": {
          "default": {
            "name": "default"
          },
          "description": "ProviderConfigReference specifies how the provider that will be used to\ncreate, observe, update, and delete this managed resource should be\nconfigured.",
          "properties": {
            "name": {
              "description": "Name of the referenced object.",
              "type": "string"
            },
            "policy": {
              "description": "Policies for referencing.",
              "properties": {
                "resolution": {
                  "default": "Required",
                  "description": "Resolution specifies whether resolution of this reference is required.\nThe default is 'Required', which means the reconcile will fail if the\nreference cannot be resolved. 'Optional' means this reference will be\na no-op if it cannot be resolved.",
                  "enum": [
                    "Required",
                    "Optional"
                  ],
                  "type": "string"
                },
                "resolve": {
                  "description": "Resolve specifies when this reference should be resolved. The default\nis 'IfNotPresent', which will attempt to resolve the reference only when\nthe corresponding field is not present. Use 'Always' to resolve the\nreference on every reconcile.",
                  "enum": [
                    "Always",
                    "IfNotPresent"
                  ],
                  "type": "string"
                }
              },
              "type": "object",
              "additionalProperties": false
            }
          },
          "required": [
            "name"
          ],
          "type": "object",
          "additionalProperties": false
        },
        "publishConnectionDetailsTo": {
          "description": "PublishConnectionDetailsTo specifies the connection secret config which\ncontains a name, metadata and a reference to secret store config to\nwhich any connection details for this managed resource should be written.\nConnection details frequently include the endpoint, username,\nand password required to connect to the managed resource.",
          "properties": {
            "configRef": {
              "default": {
                "name": "default"
              },
              "description": "SecretStoreConfigRef specifies which secret store config should be used\nfor this ConnectionSecret.",
              "properties": {
                "name": {
                  "description": "Name of the referenced object.",
                  "type": "string"
                },
                "policy": {
                  "description": "Policies for referencing.",
                  "properties": {
                    "resolution": {
                      "default": "Required",
                      "description": "Resolution specifies whether resolution of this reference is required.\nThe default is 'Required', which means the reconcile will fail if the\nreference cannot be resolved. 'Optional' means this reference will be\na no-op if it cannot be resolved.",
                      "enum": [
                        "Required",
                        "Optional"
                      ],
                      "type": "string"
                    },
                    "resolve": {
                      "description": "Resolve specifies when this reference should be resolved. The default\nis 'IfNotPresent', which will attempt to resolve the reference only when\nthe corresponding field is not present. Use 'Always' to resolve the\nreference on every reconcile.",
                      "enum": [
                        "Always",
                        "IfNotPresent"
                      ],
                      "type": "string"
                    }
                  },
                  "type": "object",
                  "additionalProperties": false
                }
              },
              "required": [
                "name"
              ],
              "type": "object",
              "additionalProperties": false
            },
            "metadata": {
              "description": "Metadata is the metadata for connection secret.",
              "properties": {
                "annotations": {
                  "additionalProperties": {
                    "type": "string"
                  },
                  "description": "Annotations are the annotations to be added to connection secret.\n- For Kubernetes secrets, this will be used as \"metadata.annotations\".\n- It is up to Secret Store implementation for others store types.",
                  "type": "object"
                },
                "labels": {
                  "additionalProperties": {
                    "type": "string"
                  },
                  "description": "Labels are the labels/tags to be added to connection secret.\n- For Kubernetes secrets, this will be used as \"metadata.labels\".\n- It is up to Secret Store implementation for others store types.",
                  "type": "object"
                },
                "type": {
                  "description": "Type is the SecretType for the connection secret.\n- Only valid for Kubernetes Secret Stores.",
                  "type": "string"
                }
              },
              "type": "object",
              "additionalProperties": false
            },
            "name": {
              "description": "Name is the name of the connection secret.",
              "type": "string"
            }
          },
          "required": [
            "name"
          ],
          "type": "object",
          "additionalProperties": false
        },
        "writeConnectionSecretToRef": {
          "description": "WriteConnectionSecretToReference specifies the namespace and name of a\nSecret to which any connection details for this managed resource should\nbe written. Connection details frequently include the endpoint, username,\nand password required to connect to the managed resource.\nThis field is planned to be replaced in a future release in favor of\nPublishConnectionDetailsTo. Currently, both could be set independently\nand connection details would be published to both without affecting\neach other.",
          "properties": {
            "name": {
              "description": "Name of the secret.",
              "type": "string"
            },
            "namespace": {
              "description": "Namespace of the secret.",
              "type": "string"
            }
          },
          "required": [
            "name",
            "namespace"
          ],
          "type": "object",
          "additionalProperties": false
        }
      },
      "required": [
        "forProvider"
      ],
      "type": "object",
      "additionalProperties": false
    },
    "status": {
      "description": "NetworkInsightsAnalysisStatus defines the observed state of NetworkInsightsAnalysis.",
      "properties": {
        "atProvider": {
          "properties": {
            "alternatePathHints": {
              "description": "Potential intermediate components of a feasible path. Described below.",
              "items": {
                "properties": {
                  "componentArn": {
                    "description": "The Amazon Resource Name (ARN) of the component.",
                    "type": "string"
                  },
                  "componentId": {
                    "description": "The ID of the component.",
                    "type": "string"
                  }
                },
                "type": "object",
                "additionalProperties": false
              },
              "type": "array"
            },
            "arn": {
              "description": "ARN of the Network Insights Analysis.",
              "type": "string"
            },
            "explanations": {
              "description": "Explanation codes for an unreachable path. See the AWS documentation for details.",
              "items": {
                "properties": {
                  "acl": {
                    "items": {
                      "properties": {
                        "arn": {
                          "description": "ARN of the Network Insights Analysis.",
                          "type": "string"
                        },
                        "id": {
                          "description": "ID of the Network Insights Analysis.",
                          "type": "string"
                        },
                        "name": {
                          "type": "string"
                        }
                      },
                      "type": "object",
                      "additionalProperties": false
                    },
                    "type": "array"
                  },
                  "aclRule": {
                    "items": {
                      "properties": {
                        "cidr": {
                          "type": "string"
                        },
                        "egress": {
                          "type": "boolean"
                        },
                        "portRange": {
                          "items": {
                            "properties": {
                              "from": {
                                "type": "number"
                              },
                              "to": {
                                "type": "number"
                              }
                            },
                            "type": "object",
                            "additionalProperties": false
                          },
                          "type": "array"
                        },
                        "protocol": {
                          "type": "string"
                        },
                        "ruleAction": {
                          "type": "string"
                        },
                        "ruleNumber": {
                          "type": "number"
                        }
                      },
                      "type": "object",
                      "additionalProperties": false
                    },
                    "type": "array"
                  },
                  "address": {
                    "type": "string"
                  },
                  "addresses": {
                    "items": {
                      "type": "string"
                    },
                    "type": "array"
                  },
                  "attachedTo": {
                    "items": {
                      "properties": {
                        "arn": {
                          "description": "ARN of the Network Insights Analysis.",
                          "type": "string"
                        },
                        "id": {
                          "description": "ID of the Network Insights Analysis.",
                          "type": "string"
                        },
                        "name": {
                          "type": "string"
                        }
                      },
                      "type": "object",
                      "additionalProperties": false
                    },
                    "type": "array"
                  },
                  "availabilityZones": {
                    "items": {
                      "type": "string"
                    },
                    "type": "array"
                  },
                  "cidrs": {
                    "items": {
                      "type": "string"
                    },
                    "type": "array"
                  },
                  "classicLoadBalancerListener": {
                    "items": {
                      "properties": {
                        "instancePort": {
                          "type": "number"
                        },
                        "loadBalancerPort": {
                          "type": "number"
                        }
                      },
                      "type": "object",
                      "additionalProperties": false
                    },
                    "type": "array"
                  },
                  "component": {
                    "items": {
                      "properties": {
                        "arn": {
                          "description": "ARN of the Network Insights Analysis.",
                          "type": "string"
                        },
                        "id": {
                          "description": "ID of the Network Insights Analysis.",
                          "type": "string"
                        },
                        "name": {
                          "type": "string"
                        }
                      },
                      "type": "object",
                      "additionalProperties": false
                    },
                    "type": "array"
                  },
                  "customerGateway": {
                    "items": {
                      "properties": {
                        "arn": {
                          "description": "ARN of the Network Insights Analysis.",
                          "type": "string"
                        },
                        "id": {
                          "description": "ID of the Network Insights Analysis.",
                          "type": "string"
                        },
                        "name": {
                          "type": "string"
                        }
                      },
                      "type": "object",
                      "additionalProperties": false
                    },
                    "type": "array"
                  },
                  "destination": {
                    "items": {
                      "properties": {
                        "arn": {
                          "description": "ARN of the Network Insights Analysis.",
                          "type": "string"
                        },
                        "id": {
                          "description": "ID of the Network Insights Analysis.",
                          "type": "string"
                        },
                        "name": {
                          "type": "string"
                        }
                      },
                      "type": "object",
                      "additionalProperties": false
                    },
                    "type": "array"
                  },
                  "destinationVpc": {
                    "items": {
                      "properties": {
                        "arn": {
                          "description": "ARN of the Network Insights Analysis.",
                          "type": "string"
                        },
                        "id": {
                          "description": "ID of the Network Insights Analysis.",
                          "type": "string"
                        },
                        "name": {
                          "type": "string"
                        }
                      },
                      "type": "object",
                      "additionalProperties": false
                    },
                    "type": "array"
                  },
                  "direction": {
                    "type": "string"
                  },
                  "elasticLoadBalancerListener": {
                    "items": {
                      "properties": {
                        "arn": {
                          "description": "ARN of the Network Insights Analysis.",
                          "type": "string"
                        },
                        "id": {
                          "description": "ID of the Network Insights Analysis.",
                          "type": "string"
                        },
                        "name": {
                          "type": "string"
                        }
                      },
                      "type": "object",
                      "additionalProperties": false
                    },
                    "type": "array"
                  },
                  "explanationCode": {
                    "type": "string"
                  },
                  "ingressRouteTable": {
                    "items": {
                      "properties": {
                        "arn": {
                          "description": "ARN of the Network Insights Analysis.",
                          "type": "string"
                        },
                        "id": {
                          "description": "ID of the Network Insights Analysis.",
                          "type": "string"
                        },
                        "name": {
                          "type": "string"
                        }
                      },
                      "type": "object",
                      "additionalProperties": false
                    },
                    "type": "array"
                  },
                  "internetGateway": {
                    "items": {
                      "properties": {
                        "arn": {
                          "description": "ARN of the Network Insights Analysis.",
                          "type": "string"
                        },
                        "id": {
                          "description": "ID of the Network Insights Analysis.",
                          "type": "string"
                        },
                        "name": {
                          "type": "string"
                        }
                      },
                      "type": "object",
                      "additionalProperties": false
                    },
                    "type": "array"
                  },
                  "loadBalancerArn": {
                    "description": "ARN of the Network Insights Analysis.",
                    "type": "string"
                  },
                  "loadBalancerListenerPort": {
                    "type": "number"
                  },
                  "loadBalancerTargetGroup": {
                    "items": {
                      "properties": {
                        "arn": {
                          "description": "ARN of the Network Insights Analysis.",
                          "type": "string"
                        },
                        "id": {
                          "description": "ID of the Network Insights Analysis.",
                          "type": "string"
                        },
                        "name": {
                          "type": "string"
                        }
                      },
                      "type": "object",
                      "additionalProperties": false
                    },
                    "type": "array"
                  },
                  "loadBalancerTargetGroups": {
                    "items": {
                      "properties": {
                        "arn": {
                          "description": "ARN of the Network Insights Analysis.",
                          "type": "string"
                        },
                        "id": {
                          "description": "ID of the Network Insights Analysis.",
                          "type": "string"
                        },
                        "name": {
                          "type": "string"
                        }
                      },
                      "type": "object",
                      "additionalProperties": false
                    },
                    "type": "array"
                  },
                  "loadBalancerTargetPort": {
                    "type": "number"
                  },
                  "missingComponent": {
                    "type": "string"
                  },
                  "natGateway": {
                    "items": {
                      "properties": {
                        "arn": {
                          "description": "ARN of the Network Insights Analysis.",
                          "type": "string"
                        },
                        "id": {
                          "description": "ID of the Network Insights Analysis.",
                          "type": "string"
                        },
                        "name": {
                          "type": "string"
                        }
                      },
                      "type": "object",
                      "additionalProperties": false
                    },
                    "type": "array"
                  },
                  "networkInterface": {
                    "items": {
                      "properties": {
                        "arn": {
                          "description": "ARN of the Network Insights Analysis.",
                          "type": "string"
                        },
                        "id": {
                          "description": "ID of the Network Insights Analysis.",
                          "type": "string"
                        },
                        "name": {
                          "type": "string"
                        }
                      },
                      "type": "object",
                      "additionalProperties": false
                    },
                    "type": "array"
                  },
                  "packetField": {
                    "type": "string"
                  },
                  "port": {
                    "type": "number"
                  },
                  "portRanges": {
                    "items": {
                      "properties": {
                        "from": {
                          "type": "number"
                        },
                        "to": {
                          "type": "number"
                        }
                      },
                      "type": "object",
                      "additionalProperties": false
                    },
                    "type": "array"
                  },
                  "prefixList": {
                    "items": {
                      "properties": {
                        "arn": {
                          "description": "ARN of the Network Insights Analysis.",
                          "type": "string"
                        },
                        "id": {
                          "description": "ID of the Network Insights Analysis.",
                          "type": "string"
                        },
                        "name": {
                          "type": "string"
                        }
                      },
                      "type": "object",
                      "additionalProperties": false
                    },
                    "type": "array"
                  },
                  "protocols": {
                    "items": {
                      "type": "string"
                    },
                    "type": "array"
                  },
                  "routeTable": {
                    "items": {
                      "properties": {
                        "arn": {
                          "description": "ARN of the Network Insights Analysis.",
                          "type": "string"
                        },
                        "id": {
                          "description": "ID of the Network Insights Analysis.",
                          "type": "string"
                        },
                        "name": {
                          "type": "string"
                        }
                      },
                      "type": "object",
                      "additionalProperties": false
                    },
                    "type": "array"
                  },
                  "routeTableRoute": {
                    "items": {
                      "properties": {
                        "destinationCidr": {
                          "type": "string"
                        },
                        "destinationPrefixListId": {
                          "description": "ID of the Network Insights Analysis.",
                          "type": "string"
                        },
                        "egressOnlyInternetGatewayId": {
                          "description": "ID of the Network Insights Analysis.",
                          "type": "string"
                        },
                        "gatewayId": {
                          "description": "ID of the Network Insights Analysis.",
                          "type": "string"
                        },
                        "instanceId": {
                          "description": "ID of the Network Insights Analysis.",
                          "type": "string"
                        },
                        "natGatewayId": {
                          "description": "ID of the Network Insights Analysis.",
                          "type": "string"
                        },
                        "networkInterfaceId": {
                          "description": "ID of the Network Insights Analysis.",
                          "type": "string"
                        },
                        "origin": {
                          "type": "string"
                        },
                        "transitGatewayId": {
                          "description": "ID of the Network Insights Analysis.",
                          "type": "string"
                        },
                        "vpcPeeringConnectionId": {
                          "description": "ID of the Network Insights Analysis.",
                          "type": "string"
                        }
                      },
                      "type": "object",
                      "additionalProperties": false
                    },
                    "type": "array"
                  },
                  "securityGroup": {
                    "items": {
                      "properties": {
                        "arn": {
                          "description": "ARN of the Network Insights Analysis.",
                          "type": "string"
                        },
                        "id": {
                          "description": "ID of the Network Insights Analysis.",
                          "type": "string"
                        },
                        "name": {
                          "type": "string"
                        }
                      },
                      "type": "object",
                      "additionalProperties": false
                    },
                    "type": "array"
                  },
                  "securityGroupRule": {
                    "items": {
                      "properties": {
                        "cidr": {
                          "type": "string"
                        },
                        "direction": {
                          "type": "string"
                        },
                        "portRange": {
                          "items": {
                            "properties": {
                              "from": {
                                "type": "number"
                              },
                              "to": {
                                "type": "number"
                              }
                            },
                            "type": "object",
                            "additionalProperties": false
                          },
                          "type": "array"
                        },
                        "prefixListId": {
                          "description": "ID of the Network Insights Analysis.",
                          "type": "string"
                        },
                        "protocol": {
                          "type": "string"
                        },
                        "securityGroupId": {
                          "description": "ID of the Network Insights Analysis.",
                          "type": "string"
                        }
                      },
                      "type": "object",
                      "additionalProperties": false
                    },
                    "type": "array"
                  },
                  "securityGroups": {
                    "items": {
                      "properties": {
                        "arn": {
                          "description": "ARN of the Network Insights Analysis.",
                          "type": "string"
                        },
                        "id": {
                          "description": "ID of the Network Insights Analysis.",
                          "type": "string"
                        },
                        "name": {
                          "type": "string"
                        }
                      },
                      "type": "object",
                      "additionalProperties": false
                    },
                    "type": "array"
                  },
                  "sourceVpc": {
                    "items": {
                      "properties": {
                        "arn": {
                          "description": "ARN of the Network Insights Analysis.",
                          "type": "string"
                        },
                        "id": {
                          "description": "ID of the Network Insights Analysis.",
                          "type": "string"
                        },
                        "name": {
                          "type": "string"
                        }
                      },
                      "type": "object",
                      "additionalProperties": false
                    },
                    "type": "array"
                  },
                  "state": {
                    "type": "string"
                  },
                  "subnet": {
                    "items": {
                      "properties": {
                        "arn": {
                          "description": "ARN of the Network Insights Analysis.",
                          "type": "string"
                        },
                        "id": {
                          "description": "ID of the Network Insights Analysis.",
                          "type": "string"
                        },
                        "name": {
                          "type": "string"
                        }
                      },
                      "type": "object",
                      "additionalProperties": false
                    },
                    "type": "array"
                  },
                  "subnetRouteTable": {
                    "items": {
                      "properties": {
                        "arn": {
                          "description": "ARN of the Network Insights Analysis.",
                          "type": "string"
                        },
                        "id": {
                          "description": "ID of the Network Insights Analysis.",
                          "type": "string"
                        },
                        "name": {
                          "type": "string"
                        }
                      },
                      "type": "object",
                      "additionalProperties": false
                    },
                    "type": "array"
                  },
                  "transitGateway": {
                    "items": {
                      "properties": {
                        "arn": {
                          "description": "ARN of the Network Insights Analysis.",
                          "type": "string"
                        },
                        "id": {
                          "description": "ID of the Network Insights Analysis.",
                          "type": "string"
                        },
                        "name": {
                          "type": "string"
                        }
                      },
                      "type": "object",
                      "additionalProperties": false
                    },
                    "type": "array"
                  },
                  "transitGatewayAttachment": {
                    "items": {
                      "properties": {
                        "arn": {
                          "description": "ARN of the Network Insights Analysis.",
                          "type": "string"
                        },
                        "id": {
                          "description": "ID of the Network Insights Analysis.",
                          "type": "string"
                        },
                        "name": {
                          "type": "string"
                        }
                      },
                      "type": "object",
                      "additionalProperties": false
                    },
                    "type": "array"
                  },
                  "transitGatewayRouteTable": {
                    "items": {
                      "properties": {
                        "arn": {
                          "description": "ARN of the Network Insights Analysis.",
                          "type": "string"
                        },
                        "id": {
                          "description": "ID of the Network Insights Analysis.",
                          "type": "string"
                        },
                        "name": {
                          "type": "string"
                        }
                      },
                      "type": "object",
                      "additionalProperties": false
                    },
                    "type": "array"
                  },
                  "transitGatewayRouteTableRoute": {
                    "items": {
                      "properties": {
                        "attachmentId": {
                          "description": "ID of the Network Insights Analysis.",
                          "type": "string"
                        },
                        "destinationCidr": {
                          "type": "string"
                        },
                        "prefixListId": {
                          "description": "ID of the Network Insights Analysis.",
                          "type": "string"
                        },
                        "resourceId": {
                          "description": "ID of the Network Insights Analysis.",
                          "type": "string"
                        },
                        "resourceType": {
                          "type": "string"
                        },
                        "routeOrigin": {
                          "type": "string"
                        },
                        "state": {
                          "type": "string"
                        }
                      },
                      "type": "object",
                      "additionalProperties": false
                    },
                    "type": "array"
                  },
                  "vpc": {
                    "items": {
                      "properties": {
                        "arn": {
                          "description": "ARN of the Network Insights Analysis.",
                          "type": "string"
                        },
                        "id": {
                          "description": "ID of the Network Insights Analysis.",
                          "type": "string"
                        },
                        "name": {
                          "type": "string"
                        }
                      },
                      "type": "object",
                      "additionalProperties": false
                    },
                    "type": "array"
                  },
                  "vpcEndpoint": {
                    "items": {
                      "properties": {
                        "arn": {
                          "description": "ARN of the Network Insights Analysis.",
                          "type": "string"
                        },
                        "id": {
                          "description": "ID of the Network Insights Analysis.",
                          "type": "string"
                        },
                        "name": {
                          "type": "string"
                        }
                      },
                      "type": "object",
                      "additionalProperties": false
                    },
                    "type": "array"
                  },
                  "vpcPeeringConnection": {
                    "items": {
                      "properties": {
                        "arn": {
                          "description": "ARN of the Network Insights Analysis.",
                          "type": "string"
                        },
                        "id": {
                          "description": "ID of the Network Insights Analysis.",
                          "type": "string"
                        },
                        "name": {
                          "type": "string"
                        }
                      },
                      "type": "object",
                      "additionalProperties": false
                    },
                    "type": "array"
                  },
                  "vpnConnection": {
                    "items": {
                      "properties": {
                        "arn": {
                          "description": "ARN of the Network Insights Analysis.",
                          "type": "string"
                        },
                        "id": {
                          "description": "ID of the Network Insights Analysis.",
                          "type": "string"
                        },
                        "name": {
                          "type": "string"
                        }
                      },
                      "type": "object",
                      "additionalProperties": false
                    },
                    "type": "array"
                  },
                  "vpnGateway": {
                    "items": {
                      "properties": {
                        "arn": {
                          "description": "ARN of the Network Insights Analysis.",
                          "type": "string"
                        },
                        "id": {
                          "description": "ID of the Network Insights Analysis.",
                          "type": "string"
                        },
                        "name": {
                          "type": "string"
                        }
                      },
                      "type": "object",
                      "additionalProperties": false
                    },
                    "type": "array"
                  }
                },
                "type": "object",
                "additionalProperties": false
              },
              "type": "array"
            },
            "filterInArns": {
              "description": "A list of ARNs for resources the path must traverse.",
              "items": {
                "type": "string"
              },
              "type": "array",
              "x-kubernetes-list-type": "set"
            },
            "forwardPathComponents": {
              "description": "The components in the path from source to destination. See the AWS documentation for details.",
              "items": {
                "properties": {
                  "aclRule": {
                    "items": {
                      "properties": {
                        "cidr": {
                          "type": "string"
                        },
                        "egress": {
                          "type": "boolean"
                        },
                        "portRange": {
                          "items": {
                            "properties": {
                              "from": {
                                "type": "number"
                              },
                              "to": {
                                "type": "number"
                              }
                            },
                            "type": "object",
                            "additionalProperties": false
                          },
                          "type": "array"
                        },
                        "protocol": {
                          "type": "string"
                        },
                        "ruleAction": {
                          "type": "string"
                        },
                        "ruleNumber": {
                          "type": "number"
                        }
                      },
                      "type": "object",
                      "additionalProperties": false
                    },
                    "type": "array"
                  },
                  "additionalDetails": {
                    "items": {
                      "properties": {
                        "additionalDetailType": {
                          "type": "string"
                        },
                        "component": {
                          "items": {
                            "properties": {
                              "arn": {
                                "description": "ARN of the Network Insights Analysis.",
                                "type": "string"
                              },
                              "id": {
                                "description": "ID of the Network Insights Analysis.",
                                "type": "string"
                              },
                              "name": {
                                "type": "string"
                              }
                            },
                            "type": "object",
                            "additionalProperties": false
                          },
                          "type": "array"
                        }
                      },
                      "type": "object",
                      "additionalProperties": false
                    },
                    "type": "array"
                  },
                  "attachedTo": {
                    "items": {
                      "properties": {
                        "arn": {
                          "description": "ARN of the Network Insights Analysis.",
                          "type": "string"
                        },
                        "id": {
                          "description": "ID of the Network Insights Analysis.",
                          "type": "string"
                        },
                        "name": {
                          "type": "string"
                        }
                      },
                      "type": "object",
                      "additionalProperties": false
                    },
                    "type": "array"
                  },
                  "component": {
                    "items": {
                      "properties": {
                        "arn": {
                          "description": "ARN of the Network Insights Analysis.",
                          "type": "string"
                        },
                        "id": {
                          "description": "ID of the Network Insights Analysis.",
                          "type": "string"
                        },
                        "name": {
                          "type": "string"
                        }
                      },
                      "type": "object",
                      "additionalProperties": false
                    },
                    "type": "array"
                  },
                  "destinationVpc": {
                    "items": {
                      "properties": {
                        "arn": {
                          "description": "ARN of the Network Insights Analysis.",
                          "type": "string"
                        },
                        "id": {
                          "description": "ID of the Network Insights Analysis.",
                          "type": "string"
                        },
                        "name": {
                          "type": "string"
                        }
                      },
                      "type": "object",
                      "additionalProperties": false
                    },
                    "type": "array"
                  },
                  "inboundHeader": {
                    "items": {
                      "properties": {
                        "destinationAddresses": {
                          "items": {
                            "type": "string"
                          },
                          "type": "array"
                        },
                        "destinationPortRanges": {
                          "items": {
                            "properties": {
                              "from": {
                                "type": "number"
                              },
                              "to": {
                                "type": "number"
                              }
                            },
                            "type": "object",
                            "additionalProperties": false
                          },
                          "type": "array"
                        },
                        "protocol": {
                          "type": "string"
                        },
                        "sourceAddresses": {
                          "items": {
                            "type": "string"
                          },
                          "type": "array"
                        },
                        "sourcePortRanges": {
                          "items": {
                            "properties": {
                              "from": {
                                "type": "number"
                              },
                              "to": {
                                "type": "number"
                              }
                            },
                            "type": "object",
                            "additionalProperties": false
                          },
                          "type": "array"
                        }
                      },
                      "type": "object",
                      "additionalProperties": false
                    },
                    "type": "array"
                  },
                  "outboundHeader": {
                    "items": {
                      "properties": {
                        "destinationAddresses": {
                          "items": {
                            "type": "string"
                          },
                          "type": "array"
                        },
                        "destinationPortRanges": {
                          "items": {
                            "properties": {
                              "from": {
                                "type": "number"
                              },
                              "to": {
                                "type": "number"
                              }
                            },
                            "type": "object",
                            "additionalProperties": false
                          },
                          "type": "array"
                        },
                        "protocol": {
                          "type": "string"
                        },
                        "sourceAddresses": {
                          "items": {
                            "type": "string"
                          },
                          "type": "array"
                        },
                        "sourcePortRanges": {
                          "items": {
                            "properties": {
                              "from": {
                                "type": "number"
                              },
                              "to": {
                                "type": "number"
                              }
                            },
                            "type": "object",
                            "additionalProperties": false
                          },
                          "type": "array"
                        }
                      },
                      "type": "object",
                      "additionalProperties": false
                    },
                    "type": "array"
                  },
                  "routeTableRoute": {
                    "items": {
                      "properties": {
                        "destinationCidr": {
                          "type": "string"
                        },
                        "destinationPrefixListId": {
                          "description": "ID of the Network Insights Analysis.",
                          "type": "string"
                        },
                        "egressOnlyInternetGatewayId": {
                          "description": "ID of the Network Insights Analysis.",
                          "type": "string"
                        },
                        "gatewayId": {
                          "description": "ID of the Network Insights Analysis.",
                          "type": "string"
                        },
                        "instanceId": {
                          "description": "ID of the Network Insights Analysis.",
                          "type": "string"
                        },
                        "natGatewayId": {
                          "description": "ID of the Network Insights Analysis.",
                          "type": "string"
                        },
                        "networkInterfaceId": {
                          "description": "ID of the Network Insights Analysis.",
                          "type": "string"
                        },
                        "origin": {
                          "type": "string"
                        },
                        "transitGatewayId": {
                          "description": "ID of the Network Insights Analysis.",
                          "type": "string"
                        },
                        "vpcPeeringConnectionId": {
                          "description": "ID of the Network Insights Analysis.",
                          "type": "string"
                        }
                      },
                      "type": "object",
                      "additionalProperties": false
                    },
                    "type": "array"
                  },
                  "securityGroupRule": {
                    "items": {
                      "properties": {
                        "cidr": {
                          "type": "string"
                        },
                        "direction": {
                          "type": "string"
                        },
                        "portRange": {
                          "items": {
                            "properties": {
                              "from": {
                                "type": "number"
                              },
                              "to": {
                                "type": "number"
                              }
                            },
                            "type": "object",
                            "additionalProperties": false
                          },
                          "type": "array"
                        },
                        "prefixListId": {
                          "description": "ID of the Network Insights Analysis.",
                          "type": "string"
                        },
                        "protocol": {
                          "type": "string"
                        },
                        "securityGroupId": {
                          "description": "ID of the Network Insights Analysis.",
                          "type": "string"
                        }
                      },
                      "type": "object",
                      "additionalProperties": false
                    },
                    "type": "array"
                  },
                  "sequenceNumber": {
                    "type": "number"
                  },
                  "sourceVpc": {
                    "items": {
                      "properties": {
                        "arn": {
                          "description": "ARN of the Network Insights Analysis.",
                          "type": "string"
                        },
                        "id": {
                          "description": "ID of the Network Insights Analysis.",
                          "type": "string"
                        },
                        "name": {
                          "type": "string"
                        }
                      },
                      "type": "object",
                      "additionalProperties": false
                    },
                    "type": "array"
                  },
                  "subnet": {
                    "items": {
                      "properties": {
                        "arn": {
                          "description": "ARN of the Network Insights Analysis.",
                          "type": "string"
                        },
                        "id": {
                          "description": "ID of the Network Insights Analysis.",
                          "type": "string"
                        },
                        "name": {
                          "type": "string"
                        }
                      },
                      "type": "object",
                      "additionalProperties": false
                    },
                    "type": "array"
                  },
                  "transitGateway": {
                    "items": {
                      "properties": {
                        "arn": {
                          "description": "ARN of the Network Insights Analysis.",
                          "type": "string"
                        },
                        "id": {
                          "description": "ID of the Network Insights Analysis.",
                          "type": "string"
                        },
                        "name": {
                          "type": "string"
                        }
                      },
                      "type": "object",
                      "additionalProperties": false
                    },
                    "type": "array"
                  },
                  "transitGatewayRouteTableRoute": {
                    "items": {
                      "properties": {
                        "attachmentId": {
                          "description": "ID of the Network Insights Analysis.",
                          "type": "string"
                        },
                        "destinationCidr": {
                          "type": "string"
                        },
                        "prefixListId": {
                          "description": "ID of the Network Insights Analysis.",
                          "type": "string"
                        },
                        "resourceId": {
                          "description": "ID of the Network Insights Analysis.",
                          "type": "string"
                        },
                        "resourceType": {
                          "type": "string"
                        },
                        "routeOrigin": {
                          "type": "string"
                        },
                        "state": {
                          "type": "string"
                        }
                      },
                      "type": "object",
                      "additionalProperties": false
                    },
                    "type": "array"
                  },
                  "vpc": {
                    "items": {
                      "properties": {
                        "arn": {
                          "description": "ARN of the Network Insights Analysis.",
                          "type": "string"
                        },
                        "id": {
                          "description": "ID of the Network Insights Analysis.",
                          "type": "string"
                        },
                        "name": {
                          "type": "string"
                        }
                      },
                      "type": "object",
                      "additionalProperties": false
                    },
                    "type": "array"
                  }
                },
                "type": "object",
                "additionalProperties": false
              },
              "type": "array"
            },
            "id": {
              "description": "ID of the Network Insights Analysis.",
              "type": "string"
            },
            "networkInsightsPathId": {
              "description": "ID of the Network Insights Path to run an analysis on.",
              "type": "string"
            },
            "pathFound": {
              "description": "Set to true if the destination was reachable.",
              "type": "boolean"
            },
            "returnPathComponents": {
              "description": "The components in the path from destination to source. See the AWS documentation for details.",
              "items": {
                "properties": {
                  "aclRule": {
                    "items": {
                      "properties": {
                        "cidr": {
                          "type": "string"
                        },
                        "egress": {
                          "type": "boolean"
                        },
                        "portRange": {
                          "items": {
                            "properties": {
                              "from": {
                                "type": "number"
                              },
                              "to": {
                                "type": "number"
                              }
                            },
                            "type": "object",
                            "additionalProperties": false
                          },
                          "type": "array"
                        },
                        "protocol": {
                          "type": "string"
                        },
                        "ruleAction": {
                          "type": "string"
                        },
                        "ruleNumber": {
                          "type": "number"
                        }
                      },
                      "type": "object",
                      "additionalProperties": false
                    },
                    "type": "array"
                  },
                  "additionalDetails": {
                    "items": {
                      "properties": {
                        "additionalDetailType": {
                          "type": "string"
                        },
                        "component": {
                          "items": {
                            "properties": {
                              "arn": {
                                "description": "ARN of the Network Insights Analysis.",
                                "type": "string"
                              },
                              "id": {
                                "description": "ID of the Network Insights Analysis.",
                                "type": "string"
                              },
                              "name": {
                                "type": "string"
                              }
                            },
                            "type": "object",
                            "additionalProperties": false
                          },
                          "type": "array"
                        }
                      },
                      "type": "object",
                      "additionalProperties": false
                    },
                    "type": "array"
                  },
                  "attachedTo": {
                    "items": {
                      "properties": {
                        "arn": {
                          "description": "ARN of the Network Insights Analysis.",
                          "type": "string"
                        },
                        "id": {
                          "description": "ID of the Network Insights Analysis.",
                          "type": "string"
                        },
                        "name": {
                          "type": "string"
                        }
                      },
                      "type": "object",
                      "additionalProperties": false
                    },
                    "type": "array"
                  },
                  "component": {
                    "items": {
                      "properties": {
                        "arn": {
                          "description": "ARN of the Network Insights Analysis.",
                          "type": "string"
                        },
                        "id": {
                          "description": "ID of the Network Insights Analysis.",
                          "type": "string"
                        },
                        "name": {
                          "type": "string"
                        }
                      },
                      "type": "object",
                      "additionalProperties": false
                    },
                    "type": "array"
                  },
                  "destinationVpc": {
                    "items": {
                      "properties": {
                        "arn": {
                          "description": "ARN of the Network Insights Analysis.",
                          "type": "string"
                        },
                        "id": {
                          "description": "ID of the Network Insights Analysis.",
                          "type": "string"
                        },
                        "name": {
                          "type": "string"
                        }
                      },
                      "type": "object",
                      "additionalProperties": false
                    },
                    "type": "array"
                  },
                  "inboundHeader": {
                    "items": {
                      "properties": {
                        "destinationAddresses": {
                          "items": {
                            "type": "string"
                          },
                          "type": "array"
                        },
                        "destinationPortRanges": {
                          "items": {
                            "properties": {
                              "from": {
                                "type": "number"
                              },
                              "to": {
                                "type": "number"
                              }
                            },
                            "type": "object",
                            "additionalProperties": false
                          },
                          "type": "array"
                        },
                        "protocol": {
                          "type": "string"
                        },
                        "sourceAddresses": {
                          "items": {
                            "type": "string"
                          },
                          "type": "array"
                        },
                        "sourcePortRanges": {
                          "items": {
                            "properties": {
                              "from": {
                                "type": "number"
                              },
                              "to": {
                                "type": "number"
                              }
                            },
                            "type": "object",
                            "additionalProperties": false
                          },
                          "type": "array"
                        }
                      },
                      "type": "object",
                      "additionalProperties": false
                    },
                    "type": "array"
                  },
                  "outboundHeader": {
                    "items": {
                      "properties": {
                        "destinationAddresses": {
                          "items": {
                            "type": "string"
                          },
                          "type": "array"
                        },
                        "destinationPortRanges": {
                          "items": {
                            "properties": {
                              "from": {
                                "type": "number"
                              },
                              "to": {
                                "type": "number"
                              }
                            },
                            "type": "object",
                            "additionalProperties": false
                          },
                          "type": "array"
                        },
                        "protocol": {
                          "type": "string"
                        },
                        "sourceAddresses": {
                          "items": {
                            "type": "string"
                          },
                          "type": "array"
                        },
                        "sourcePortRanges": {
                          "items": {
                            "properties": {
                              "from": {
                                "type": "number"
                              },
                              "to": {
                                "type": "number"
                              }
                            },
                            "type": "object",
                            "additionalProperties": false
                          },
                          "type": "array"
                        }
                      },
                      "type": "object",
                      "additionalProperties": false
                    },
                    "type": "array"
                  },
                  "routeTableRoute": {
                    "items": {
                      "properties": {
                        "destinationCidr": {
                          "type": "string"
                        },
                        "destinationPrefixListId": {
                          "description": "ID of the Network Insights Analysis.",
                          "type": "string"
                        },
                        "egressOnlyInternetGatewayId": {
                          "description": "ID of the Network Insights Analysis.",
                          "type": "string"
                        },
                        "gatewayId": {
                          "description": "ID of the Network Insights Analysis.",
                          "type": "string"
                        },
                        "instanceId": {
                          "description": "ID of the Network Insights Analysis.",
                          "type": "string"
                        },
                        "natGatewayId": {
                          "description": "ID of the Network Insights Analysis.",
                          "type": "string"
                        },
                        "networkInterfaceId": {
                          "description": "ID of the Network Insights Analysis.",
                          "type": "string"
                        },
                        "origin": {
                          "type": "string"
                        },
                        "transitGatewayId": {
                          "description": "ID of the Network Insights Analysis.",
                          "type": "string"
                        },
                        "vpcPeeringConnectionId": {
                          "description": "ID of the Network Insights Analysis.",
                          "type": "string"
                        }
                      },
                      "type": "object",
                      "additionalProperties": false
                    },
                    "type": "array"
                  },
                  "securityGroupRule": {
                    "items": {
                      "properties": {
                        "cidr": {
                          "type": "string"
                        },
                        "direction": {
                          "type": "string"
                        },
                        "portRange": {
                          "items": {
                            "properties": {
                              "from": {
                                "type": "number"
                              },
                              "to": {
                                "type": "number"
                              }
                            },
                            "type": "object",
                            "additionalProperties": false
                          },
                          "type": "array"
                        },
                        "prefixListId": {
                          "description": "ID of the Network Insights Analysis.",
                          "type": "string"
                        },
                        "protocol": {
                          "type": "string"
                        },
                        "securityGroupId": {
                          "description": "ID of the Network Insights Analysis.",
                          "type": "string"
                        }
                      },
                      "type": "object",
                      "additionalProperties": false
                    },
                    "type": "array"
                  },
                  "sequenceNumber": {
                    "type": "number"
                  },
                  "sourceVpc": {
                    "items": {
                      "properties": {
                        "arn": {
                          "description": "ARN of the Network Insights Analysis.",
                          "type": "string"
                        },
                        "id": {
                          "description": "ID of the Network Insights Analysis.",
                          "type": "string"
                        },
                        "name": {
                          "type": "string"
                        }
                      },
                      "type": "object",
                      "additionalProperties": false
                    },
                    "type": "array"
                  },
                  "subnet": {
                    "items": {
                      "properties": {
                        "arn": {
                          "description": "ARN of the Network Insights Analysis.",
                          "type": "string"
                        },
                        "id": {
                          "description": "ID of the Network Insights Analysis.",
                          "type": "string"
                        },
                        "name": {
                          "type": "string"
                        }
                      },
                      "type": "object",
                      "additionalProperties": false
                    },
                    "type": "array"
                  },
                  "transitGateway": {
                    "items": {
                      "properties": {
                        "arn": {
                          "description": "ARN of the Network Insights Analysis.",
                          "type": "string"
                        },
                        "id": {
                          "description": "ID of the Network Insights Analysis.",
                          "type": "string"
                        },
                        "name": {
                          "type": "string"
                        }
                      },
                      "type": "object",
                      "additionalProperties": false
                    },
                    "type": "array"
                  },
                  "transitGatewayRouteTableRoute": {
                    "items": {
                      "properties": {
                        "attachmentId": {
                          "description": "ID of the Network Insights Analysis.",
                          "type": "string"
                        },
                        "destinationCidr": {
                          "type": "string"
                        },
                        "prefixListId": {
                          "description": "ID of the Network Insights Analysis.",
                          "type": "string"
                        },
                        "resourceId": {
                          "description": "ID of the Network Insights Analysis.",
                          "type": "string"
                        },
                        "resourceType": {
                          "type": "string"
                        },
                        "routeOrigin": {
                          "type": "string"
                        },
                        "state": {
                          "type": "string"
                        }
                      },
                      "type": "object",
                      "additionalProperties": false
                    },
                    "type": "array"
                  },
                  "vpc": {
                    "items": {
                      "properties": {
                        "arn": {
                          "description": "ARN of the Network Insights Analysis.",
                          "type": "string"
                        },
                        "id": {
                          "description": "ID of the Network Insights Analysis.",
                          "type": "string"
                        },
                        "name": {
                          "type": "string"
                        }
                      },
                      "type": "object",
                      "additionalProperties": false
                    },
                    "type": "array"
                  }
                },
                "type": "object",
                "additionalProperties": false
              },
              "type": "array"
            },
            "startDate": {
              "description": "The date/time the analysis was started.",
              "type": "string"
            },
            "status": {
              "description": "The status of the analysis. succeeded means the analysis was completed, not that a path was found, for that see path_found.",
              "type": "string"
            },
            "statusMessage": {
              "description": "A message to provide more context when the status is failed.",
              "type": "string"
            },
            "tags": {
              "additionalProperties": {
                "type": "string"
              },
              "description": "Key-value map of resource tags.",
              "type": "object",
              "x-kubernetes-map-type": "granular"
            },
            "tagsAll": {
              "additionalProperties": {
                "type": "string"
              },
              "description": "Map of tags assigned to the resource, including those inherited from the provider default_tags configuration block.",
              "type": "object",
              "x-kubernetes-map-type": "granular"
            },
            "waitForCompletion": {
              "description": "If enabled, the resource will wait for the Network Insights Analysis status to change to succeeded or failed. Setting this to false will skip the process. Default: true.",
              "type": "boolean"
            },
            "warningMessage": {
              "description": "The warning message.",
              "type": "string"
            }
          },
          "type": "object",
          "additionalProperties": false
        },
        "conditions": {
          "description": "Conditions of the resource.",
          "items": {
            "description": "A Condition that may apply to a resource.",
            "properties": {
              "lastTransitionTime": {
                "description": "LastTransitionTime is the last time this condition transitioned from one\nstatus to another.",
                "format": "date-time",
                "type": "string"
              },
              "message": {
                "description": "A Message containing details about this condition's last transition from\none status to another, if any.",
                "type": "string"
              },
              "observedGeneration": {
                "description": "ObservedGeneration represents the .metadata.generation that the condition was set based upon.\nFor instance, if .metadata.generation is currently 12, but the .status.conditions[x].observedGeneration is 9, the condition is out of date\nwith respect to the current state of the instance.",
                "format": "int64",
                "type": "integer"
              },
              "reason": {
                "description": "A Reason for this condition's last transition from one status to another.",
                "type": "string"
              },
              "status": {
                "description": "Status of this condition; is it currently True, False, or Unknown?",
                "type": "string"
              },
              "type": {
                "description": "Type of this condition. At most one of each condition type may apply to\na resource at any point in time.",
                "type": "string"
              }
            },
            "required": [
              "lastTransitionTime",
              "reason",
              "status",
              "type"
            ],
            "type": "object",
            "additionalProperties": false
          },
          "type": "array",
          "x-kubernetes-list-map-keys": [
            "type"
          ],
          "x-kubernetes-list-type": "map"
        },
        "observedGeneration": {
          "description": "ObservedGeneration is the latest metadata.generation\nwhich resulted in either a ready state, or stalled due to error\nit can not recover from without human intervention.",
          "format": "int64",
          "type": "integer"
        }
      },
      "type": "object",
      "additionalProperties": false
    }
  },
  "required": [
    "spec"
  ],
  "type": "object"
}
