{
  "description": "A ManagedResourceActivationPolicy defines the activation policy for ManagedResourceDefinitions.",
  "properties": {
    "apiVersion": {
      "description": "APIVersion defines the versioned schema of this representation of an object.\nServers should convert recognized schemas to the latest internal value, and\nmay reject unrecognized values.\nMore info: https://git.k8s.io/community/contributors/devel/sig-architecture/api-conventions.md#resources",
      "type": "string"
    },
    "kind": {
      "description": "Kind is a string value representing the REST resource this object represents.\nServers may infer this from the endpoint the client submits requests to.\nCannot be updated.\nIn CamelCase.\nMore info: https://git.k8s.io/community/contributors/devel/sig-architecture/api-conventions.md#types-kinds",
      "type": "string"
    },
    "metadata": {
      "type": "object"
    },
    "spec": {
      "description": "ManagedResourceActivationPolicySpec specifies the desired activation state of ManagedResourceDefinitions.",
      "properties": {
        "activate": {
          "description": "Activations is an array of MRD names to activate. Supports wildcard\nprefixes (like `*.aws.crossplane.io`) but not full regular expressions.",
          "items": {
            "description": "ActivationPolicy matches on MRD names with wildcard prefix support.",
            "type": "string"
          },
          "minItems": 1,
          "type": "array"
        }
      },
      "required": [
        "activate"
      ],
      "type": "object",
      "additionalProperties": false
    },
    "status": {
      "description": "ManagedResourceActivationPolicyStatus shows the observed state of the policy.",
      "properties": {
        "activated": {
          "description": "Activated names the ManagedResourceDefinitions this policy has activated.",
          "items": {
            "type": "string"
          },
          "type": "array"
        },
        "conditions": {
          "description": "Conditions of the resource.",
          "items": {
            "description": "A Condition that may apply to a resource.",
            "properties": {
              "lastTransitionTime": {
                "description": "LastTransitionTime is the last time this condition transitioned from one\nstatus to another.",
                "format": "date-time",
                "type": "string"
              },
              "message": {
                "description": "A Message containing details about this condition's last transition from\none status to another, if any.",
                "type": "string"
              },
              "observedGeneration": {
                "description": "ObservedGeneration represents the .metadata.generation that the condition was set based upon.\nFor instance, if .metadata.generation is currently 12, but the .status.conditions[x].observedGeneration is 9, the condition is out of date\nwith respect to the current state of the instance.",
                "format": "int64",
                "type": "integer"
              },
              "reason": {
                "description": "A Reason for this condition's last transition from one status to another.",
                "type": "string"
              },
              "status": {
                "description": "Status of this condition; is it currently True, False, or Unknown?",
                "type": "string"
              },
              "type": {
                "description": "Type of this condition. At most one of each condition type may apply to\na resource at any point in time.",
                "type": "string"
              }
            },
            "required": [
              "lastTransitionTime",
              "reason",
              "status",
              "type"
            ],
            "type": "object",
            "additionalProperties": false
          },
          "type": "array",
          "x-kubernetes-list-map-keys": [
            "type"
          ],
          "x-kubernetes-list-type": "map"
        }
      },
      "type": "object",
      "additionalProperties": false
    }
  },
  "type": "object"
}
