{
    "oneOf": [
        {
            "$ref": "apirequestcount_apiserver.openshift.io_v1.json"
        },
        {
            "$ref": "deploymentconfig_apps.openshift.io_v1.json"
        },
        {
            "$ref": "clusterrolebinding_authorization.openshift.io_v1.json"
        },
        {
            "$ref": "clusterrole_authorization.openshift.io_v1.json"
        },
        {
            "$ref": "rolebindingrestriction_authorization.openshift.io_v1.json"
        },
        {
            "$ref": "rolebinding_authorization.openshift.io_v1.json"
        },
        {
            "$ref": "role_authorization.openshift.io_v1.json"
        },
        {
            "$ref": "binarybuildrequestoptions_build.openshift.io_v1.json"
        },
        {
            "$ref": "buildconfig_build.openshift.io_v1.json"
        },
        {
            "$ref": "buildrequest_build.openshift.io_v1.json"
        },
        {
            "$ref": "build_build.openshift.io_v1.json"
        },
        {
            "$ref": "cloudprivateipconfig_cloud.network.openshift.io_v1.json"
        },
        {
            "$ref": "apiserver_config.openshift.io_v1.json"
        },
        {
            "$ref": "authentication_config.openshift.io_v1.json"
        },
        {
            "$ref": "backup_config.openshift.io_v1alpha1.json"
        },
        {
            "$ref": "build_config.openshift.io_v1.json"
        },
        {
            "$ref": "clusteroperator_config.openshift.io_v1.json"
        },
        {
            "$ref": "clusterversion_config.openshift.io_v1.json"
        },
        {
            "$ref": "console_config.openshift.io_v1.json"
        },
        {
            "$ref": "dns_config.openshift.io_v1.json"
        },
        {
            "$ref": "featuregate_config.openshift.io_v1.json"
        },
        {
            "$ref": "imagecontentpolicy_config.openshift.io_v1.json"
        },
        {
            "$ref": "imagedigestmirrorset_config.openshift.io_v1.json"
        },
        {
            "$ref": "image_config.openshift.io_v1.json"
        },
        {
            "$ref": "imagetagmirrorset_config.openshift.io_v1.json"
        },
        {
            "$ref": "infrastructure_config.openshift.io_v1.json"
        },
        {
            "$ref": "ingress_config.openshift.io_v1.json"
        },
        {
            "$ref": "insightsdatagather_config.openshift.io_v1alpha1.json"
        },
        {
            "$ref": "network_config.openshift.io_v1.json"
        },
        {
            "$ref": "node_config.openshift.io_v1.json"
        },
        {
            "$ref": "oauth_config.openshift.io_v1.json"
        },
        {
            "$ref": "operatorhub_config.openshift.io_v1.json"
        },
        {
            "$ref": "project_config.openshift.io_v1.json"
        },
        {
            "$ref": "proxy_config.openshift.io_v1.json"
        },
        {
            "$ref": "scheduler_config.openshift.io_v1.json"
        },
        {
            "$ref": "consoleclidownload_console.openshift.io_v1.json"
        },
        {
            "$ref": "consoleexternalloglink_console.openshift.io_v1.json"
        },
        {
            "$ref": "consolelink_console.openshift.io_v1.json"
        },
        {
            "$ref": "consolenotification_console.openshift.io_v1.json"
        },
        {
            "$ref": "consoleplugin_console.openshift.io_v1.json"
        },
        {
            "$ref": "consolequickstart_console.openshift.io_v1.json"
        },
        {
            "$ref": "consolesample_console.openshift.io_v1.json"
        },
        {
            "$ref": "consoleyamlsample_console.openshift.io_v1.json"
        },
        {
            "$ref": "podnetworkconnectivitycheck_controlplane.operator.openshift.io_v1alpha1.json"
        },
        {
            "$ref": "notstableconfigtype_example.openshift.io_v1alpha1.json"
        },
        {
            "$ref": "stableconfigtype_example.openshift.io_v1.json"
        },
        {
            "$ref": "helmchartrepository_helm.openshift.io_v1beta1.json"
        },
        {
            "$ref": "projecthelmchartrepository_helm.openshift.io_v1beta1.json"
        },
        {
            "$ref": "imagesignature_image.openshift.io_v1.json"
        },
        {
            "$ref": "imagestreamimage_image.openshift.io_v1.json"
        },
        {
            "$ref": "imagestreamimport_image.openshift.io_v1.json"
        },
        {
            "$ref": "imagestreamlayers_image.openshift.io_v1.json"
        },
        {
            "$ref": "imagestreammapping_image.openshift.io_v1.json"
        },
        {
            "$ref": "imagestream_image.openshift.io_v1.json"
        },
        {
            "$ref": "imagestreamtag_image.openshift.io_v1.json"
        },
        {
            "$ref": "image_image.openshift.io_v1.json"
        },
        {
            "$ref": "imagetag_image.openshift.io_v1.json"
        },
        {
            "$ref": "config_imageregistry.operator.openshift.io_v1.json"
        },
        {
            "$ref": "imagepruner_imageregistry.operator.openshift.io_v1.json"
        },
        {
            "$ref": "dnsrecord_ingress.operator.openshift.io_v1.json"
        },
        {
            "$ref": "datagather_insights.openshift.io_v1alpha1.json"
        },
        {
            "$ref": "containerruntimeconfig_machineconfiguration.openshift.io_v1.json"
        },
        {
            "$ref": "controllerconfig_machineconfiguration.openshift.io_v1.json"
        },
        {
            "$ref": "kubeletconfig_machineconfiguration.openshift.io_v1.json"
        },
        {
            "$ref": "machineconfignode_machineconfiguration.openshift.io_v1alpha1.json"
        },
        {
            "$ref": "machineconfigpool_machineconfiguration.openshift.io_v1.json"
        },
        {
            "$ref": "machineconfig_machineconfiguration.openshift.io_v1.json"
        },
        {
            "$ref": "alibabacloudmachineproviderconfig_machine.openshift.io_v1.json"
        },
        {
            "$ref": "alibabacloudmachineproviderstatus_machine.openshift.io_v1.json"
        },
        {
            "$ref": "awsmachineproviderconfig_machine.openshift.io_v1beta1.json"
        },
        {
            "$ref": "azuremachineproviderspec_machine.openshift.io_v1beta1.json"
        },
        {
            "$ref": "azuremachineproviderstatus_machine.openshift.io_v1beta1.json"
        },
        {
            "$ref": "controlplanemachineset_machine.openshift.io_v1.json"
        },
        {
            "$ref": "gcpmachineproviderspec_machine.openshift.io_v1beta1.json"
        },
        {
            "$ref": "gcpmachineproviderstatus_machine.openshift.io_v1beta1.json"
        },
        {
            "$ref": "machinehealthcheck_machine.openshift.io_v1beta1.json"
        },
        {
            "$ref": "machineset_machine.openshift.io_v1beta1.json"
        },
        {
            "$ref": "machine_machine.openshift.io_v1beta1.json"
        },
        {
            "$ref": "nutanixmachineproviderconfig_machine.openshift.io_v1.json"
        },
        {
            "$ref": "openstackproviderspec_machine.openshift.io_v1alpha1.json"
        },
        {
            "$ref": "powervsmachineproviderconfig_machine.openshift.io_v1.json"
        },
        {
            "$ref": "vspheremachineproviderspec_machine.openshift.io_v1beta1.json"
        },
        {
            "$ref": "alertingrule_monitoring.openshift.io_v1.json"
        },
        {
            "$ref": "alertrelabelconfig_monitoring.openshift.io_v1.json"
        },
        {
            "$ref": "clusternetwork_network.openshift.io_v1.json"
        },
        {
            "$ref": "dnsnameresolver_network.openshift.io_v1alpha1.json"
        },
        {
            "$ref": "egressnetworkpolicy_network.openshift.io_v1.json"
        },
        {
            "$ref": "hostsubnet_network.openshift.io_v1.json"
        },
        {
            "$ref": "netnamespace_network.openshift.io_v1.json"
        },
        {
            "$ref": "egressrouter_network.operator.openshift.io_v1.json"
        },
        {
            "$ref": "oauthaccesstoken_oauth.openshift.io_v1.json"
        },
        {
            "$ref": "oauthauthorizetoken_oauth.openshift.io_v1.json"
        },
        {
            "$ref": "oauthclientauthorization_oauth.openshift.io_v1.json"
        },
        {
            "$ref": "oauthclient_oauth.openshift.io_v1.json"
        },
        {
            "$ref": "oauthredirectreference_oauth.openshift.io_v1.json"
        },
        {
            "$ref": "authentication_operator.openshift.io_v1.json"
        },
        {
            "$ref": "cloudcredential_operator.openshift.io_v1.json"
        },
        {
            "$ref": "clustercsidriver_operator.openshift.io_v1.json"
        },
        {
            "$ref": "config_operator.openshift.io_v1.json"
        },
        {
            "$ref": "console_operator.openshift.io_v1.json"
        },
        {
            "$ref": "csisnapshotcontroller_operator.openshift.io_v1.json"
        },
        {
            "$ref": "dns_operator.openshift.io_v1.json"
        },
        {
            "$ref": "etcdbackup_operator.openshift.io_v1alpha1.json"
        },
        {
            "$ref": "etcd_operator.openshift.io_v1.json"
        },
        {
            "$ref": "imagecontentsourcepolicy_operator.openshift.io_v1alpha1.json"
        },
        {
            "$ref": "ingresscontroller_operator.openshift.io_v1.json"
        },
        {
            "$ref": "insightsoperator_operator.openshift.io_v1.json"
        },
        {
            "$ref": "kubeapiserver_operator.openshift.io_v1.json"
        },
        {
            "$ref": "kubecontrollermanager_operator.openshift.io_v1.json"
        },
        {
            "$ref": "kubescheduler_operator.openshift.io_v1.json"
        },
        {
            "$ref": "kubestorageversionmigrator_operator.openshift.io_v1.json"
        },
        {
            "$ref": "machineconfiguration_operator.openshift.io_v1.json"
        },
        {
            "$ref": "myoperatorresource_operator.openshift.io_v1.json"
        },
        {
            "$ref": "network_operator.openshift.io_v1.json"
        },
        {
            "$ref": "olm_operator.openshift.io_v1alpha1.json"
        },
        {
            "$ref": "openshiftapiserver_operator.openshift.io_v1.json"
        },
        {
            "$ref": "openshiftcontrollermanager_operator.openshift.io_v1.json"
        },
        {
            "$ref": "serviceca_operator.openshift.io_v1.json"
        },
        {
            "$ref": "servicecatalogapiserver_operator.openshift.io_v1.json"
        },
        {
            "$ref": "servicecatalogcontrollermanager_operator.openshift.io_v1.json"
        },
        {
            "$ref": "storage_operator.openshift.io_v1.json"
        },
        {
            "$ref": "platformoperator_platform.openshift.io_v1alpha1.json"
        },
        {
            "$ref": "projectrequest_project.openshift.io_v1.json"
        },
        {
            "$ref": "project_project.openshift.io_v1.json"
        },
        {
            "$ref": "appliedclusterresourcequota_quota.openshift.io_v1.json"
        },
        {
            "$ref": "clusterresourcequota_quota.openshift.io_v1.json"
        },
        {
            "$ref": "route_route.openshift.io_v1.json"
        },
        {
            "$ref": "config_samples.operator.openshift.io_v1.json"
        },
        {
            "$ref": "rangeallocation_security.internal.openshift.io_v1.json"
        },
        {
            "$ref": "rangeallocation_security.openshift.io_v1.json"
        },
        {
            "$ref": "securitycontextconstraints_security.openshift.io_v1.json"
        },
        {
            "$ref": "servicecertsigneroperatorconfig_servicecertsigner.config.openshift.io_v1alpha1.json"
        },
        {
            "$ref": "sharedconfigmap_sharedresource.openshift.io_v1alpha1.json"
        },
        {
            "$ref": "sharedsecret_sharedresource.openshift.io_v1alpha1.json"
        },
        {
            "$ref": "brokertemplateinstance_template.openshift.io_v1.json"
        },
        {
            "$ref": "templateinstance_template.openshift.io_v1.json"
        },
        {
            "$ref": "template_template.openshift.io_v1.json"
        },
        {
            "$ref": "group_user.openshift.io_v1.json"
        },
        {
            "$ref": "identity_user.openshift.io_v1.json"
        },
        {
            "$ref": "useridentitymapping_user.openshift.io_v1.json"
        },
        {
            "$ref": "user_user.openshift.io_v1.json"
        }
    ]
}
